pysmms/__init__.py
pysmms/git_upload.py
pysmms/help.py
pysmms/history.py
pysmms/ip_history.py
pysmms/profile.py
pysmms/pysmms.py
pysmms/upload.py
pysmms/utils.py
tests/__init__.py
tests/test.py
pysmms-0.1.5.dist-info/LICENSE
pysmms-0.1.5.dist-info/METADATA
pysmms-0.1.5.dist-info/WHEEL
pysmms-0.1.5.dist-info/entry_points.txt
pysmms-0.1.5.dist-info/top_level.txt
pysmms-0.1.5.dist-info/RECORD
