Metadata-Version: 2.1
Name: pysmms
Version: 0.1.5
Summary: The CLI Tool for SM.MS, based on API v2.
Home-page: https://github.com/pysmms/pysmms
Author: Jianxun
Author-email: i@lijianxun.top
License: UNKNOWN
Platform: UNKNOWN
Classifier: Programming Language :: Python :: 3
Classifier: License :: OSI Approved :: GNU General Public License v3 (GPLv3)
Classifier: Operating System :: OS Independent
Requires-Dist: requests
Requires-Dist: pyperclip
Requires-Dist: terminaltables
